{"Cagayan de Oro": {"size": 46, "country": "Philippines", "full_desc": ["largest", "mall", "cayagan", "de", "oro", "large", "busy", "mall", "second", "largest", "mall", "cagayan", "de", "oro", "many", "restaurants", "large", "supermarket", "robinson", "department", "store", "stop", "airport", "busses", "many", "stores", "cdo", "174", "399", "sm", "shopping", "mall", "savemore", "supermarket", "need", "two", "kgs", "washing", "master", "card", "visa", "card", "atm", "km", "kauswagan", "filipino", "seafood", "cuisine", "kagay", "anon", "restaurant", "limketkai", "center", "filipino", "cuisine", "ostrich", "meat", "la", "tegola", "archbishop", "hayes", "st", "italian", "restaurant", "quiet", "comfortable", "favorite", "foreign", "visitors", "wanting", "great", "italian", "meal", "good", "bottle", "wine", "vienna", "kaffehaus", "velez", "st", "european", "western", "style", "dishes", "classy", "ambience", "combined", "french", "mediterranean", "cuisines", "executive", "chef", "switzerland", "great", "foods", "ranging", "asian", "western", "style", "dishes", "p", "99", "get", "pork", "hamonada", "roast", "beef", "kilawin", "sisig", "chopsuey", "chicken", "nuggets", "tapioca", "chocolate", "cake", "soup", "iced", "tea", "batchoy", "p20", "gato", "p30", "lugaw", "p15", "zeki", "p55", "sort", "drinks", "p10", "great", "foods", "ranging", "asian", "western", "style", "dishes", "coffee", "shop", "pinoy", "indian", "cuisine", "wi", "fi", "zone", "aircon", "wifi", "laundry", "service", "fan", "double", "rooms", "outside", "bathrooms", "c", "double", "rooms", "outside", "bathrooms", "rooms", "cable", "tv", "phone", "free", "wifi", "pay", "master", "card", "visa", "card", "economy", "c", "single", "rooms", "bathroom", "cable", "tv", "economy", "c", "double", "rooms", "bathroom", "cable", "tv", "standard", "c", "double", "rooms", "deluxe", "c", "double", "rooms", "c", "single", "double", "rooms", "hot", "water", "bathrooms", "cable", "tv", "free", "wifi", "economy", "c", "single", "double", "rooms", "hot", "water", "bathrooms", "cable", "tv", "free", "wifi", "fan", "rooms", "12", "hours", "c", "rooms", "12", "hours", "c", "rooms", "24", "hours", "common", "bathrooms", "free", "wifi", "c", "single", "room", "hot", "water", "bathroom", "cable", "tv", "c", "economy", "double", "room", "hot", "water", "bathroom", "cable", "tv", "c", "rooms", "bathroom", "12", "24", "hours", "c", "single", "double", "rooms", "bathrooms", "cable", "tv", "gv", "hotel", "cdo", "102", "rooms", "c", "double", "rooms", "bathrooms", "cable", "tv", "7", "hours", "12", "hours", "24", "hours", "c", "single", "rooms", "bathroom", "cable", "tv", "c", "double", "rooms", "hot", "water", "bathroom", "cable", "tv", "rooms", "free", "wifi", "single", "room", "economy", "double", "standard", "double", "de", "luxe", "good", "3", "persons", "rooms", "c", "lcd", "tv", "hot", "water", "c", "rooms", "bathrooms", "cable", "tv", "c", "single", "double", "rooms", "hot", "water", "bathroom", "cable", "tv", "wifi", "zone", "standby", "generator", "telephone", "room", "monday", "till", "wednesday", "rooms", "500", "16", "18", "bed", "dorm", "c", "c", "economy", "double", "bathroom", "cable", "tv", "c", "standard", "double", "bathroom", "cable", "tv", "c", "single", "double", "rooms", "hot", "water", "bathroom", "cable", "tv", "free", "wifi", "41", "rooms", "dorm", "beds", "c", "double", "rooms", "bathroom", "cable", "tv", "free", "wifi", "c", "double", "rooms", "bathroom", "cable", "tv", "pryce", "plaza", "located", "cagayan", "de", "oro", "city", "philippines", "offers", "80", "air", "conditioned", "rooms", "suites", "mini", "bar", "cable", "tv", "idd", "phone", "extension", "bathroom", "amenities", "include", "elite", "spa", "fitness", "club", "swimming", "pool", "restaurants", "cafe", "cagayan", "compadres", "bar", "josefina", "seafood", "grill", "japanese", "corner", "staying", "visit", "interesting", "places", "like", "la", "castilla", "museum", "migtugsok", "falls", "macahambus", "hill", "cave", "located", "within", "xavier", "estates", "complex", "every", "room", "air", "conditioning", "pocket", "refrigerator", "mini", "bar", "cable", "tv", "high", "speed", "internet", "access", "amenities", "fitness", "room", "game", "room", "restaurant", "cafe", "bar", "lounge", "outdoor", "swimming", "pool", "rooms", "executive", "work", "desk", "mini", "bar", "coffee", "tea", "making", "facilities", "room", "safe", "restaurant", "lounge", "meeting", "rooms", "gym", "adult", "children", "pool", "room", "massage", "currency", "exchange", "parking", "safety", "deposit", "boxes", "airport", "city", "transfers", "laundry", "dry", "cleaning", "vamenta", "blvd", "carmen", "mastersons", "ave", "upper", "carmen", "5", "minutes", "lumbia", "airport", "sits", "adjacent", "pueblo", "de", "oro", "golf", "course", "lies", "opposite", "xavier", "estates", "sports", "country", "club", "phone", "number", "63", "88", "858", "5696", "price", "php", "1", "120", "00", "unique", "beautiful", "place", "please", "read", "description", "see", "section", "unique", "philippines", "european", "style", "bed", "breakfast", "relaxing", "stunning", "view", "capt", "vicente", "roa", "st", "florentino", "st", "limketkai", "center"], "attractions": {"Limketkai Center": {"type": "buy", "description": ["largest", "mall", "cayagan", "de", "oro"], "coordinates": [NaN, NaN], "website": "http://www.limketkaicenter.com", "place_id": "ChIJM2uLQcTy_zIRrMTzck1fv6A", "reviews": null}, "Gaisano City Mall & Gaisano Supermarket.": {"type": "buy", "description": ["large", "busy", "mall"], "coordinates": [8.4864, 124.6514], "website": "nan", "place_id": "ChIJHaMyCd3y_zIRuyMC_3lnmFQ", "reviews": null}, "Shopwise Hypermarket.": {"type": "buy", "description": ["nan"], "coordinates": [NaN, NaN], "website": "http://www.shopwise.com.ph", "place_id": "ChIJxx_5o8by_zIR9QFylCecCaM", "reviews": null}, "Centrio Ayala mall": {"type": "buy", "description": ["second", "largest", "mall", "cagayan", "de", "oro", "many", "restaurants", "large", "supermarket", "robinson", "department", "store", "stop", "airport", "busses"], "coordinates": [8.4849, 124.65100000000001], "website": "http://www.ayalamalls.com.ph", "place_id": "ChIJJ-F_4dzy_zIRP8Q_gyWz37c", "reviews": null}, "Puregold Hypermarket.": {"type": "buy", "description": ["nan"], "coordinates": [NaN, NaN], "website": "nan", "place_id": "ChIJqwGPqzjAATMRZ1RMxIDanNA", "reviews": null}, "7-Eleven": {"type": "buy", "description": ["many", "stores", "cdo"], "coordinates": [NaN, NaN], "website": "nan", "place_id": "ChIJq0BoRv-kskwREgnjqcbzLYM", "reviews": null}, "SM Cagayan de Oro Premier": {"type": "buy", "description": ["174", "399", "sm", "shopping", "mall", "savemore", "supermarket"], "coordinates": [NaN, NaN], "website": "http://www.smsupermalls.com", "place_id": "ChIJsSwPbDfz_zIR3XLnrsKaCpQ", "reviews": null}, "Mrs Labada Laundry station.": {"type": "buy", "description": ["need", "two", "kgs", "washing"], "coordinates": [NaN, NaN], "website": "nan", "place_id": "ChIJbRhM-9by_zIRPmTQJrwjEqg", "reviews": null}, "Bank of the Philippines islands.": {"type": "buy", "description": ["master", "card", "visa", "card", "atm"], "coordinates": [NaN, NaN], "website": "nan", "place_id": "ChIJ341ledfy_zIRgqYciJqtb0c", "reviews": null}, "Dadang's Seafoods Restaurant": {"type": "eat", "description": ["km", "kauswagan", "filipino", "seafood", "cuisine", "kagay", "anon", "restaurant", "limketkai", "center", "filipino", "cuisine", "ostrich", "meat", "la", "tegola", "archbishop", "hayes", "st", "italian", "restaurant", "quiet", "comfortable", "favorite", "foreign", "visitors", "wanting", "great", "italian", "meal", "good", "bottle", "wine", "vienna", "kaffehaus", "velez", "st", "european", "western", "style", "dishes"], "coordinates": [NaN, NaN], "website": "nan", "place_id": "ChIJQ_i8Y8Py_zIRf71Yoyvf6J8", "reviews": null}, "La Vetta Wine Bar and Restaurant": {"type": "eat", "description": ["classy", "ambience", "combined", "french", "mediterranean", "cuisines", "executive", "chef", "switzerland"], "coordinates": [NaN, NaN], "website": "nan", "place_id": "ChIJr2DWi8Py_zIRjc1Xhz3zqtg", "reviews": null}, "Sentro 1850": {"type": "drink", "description": ["great", "foods", "ranging", "asian", "western", "style", "dishes"], "coordinates": [NaN, NaN], "website": "nan", "place_id": "ChIJXywkUdby_zIRTIw2Amn1NtY", "reviews": null}, "99 Ranch Eat all you can": {"type": "eat", "description": ["p", "99", "get", "pork", "hamonada", "roast", "beef", "kilawin", "sisig", "chopsuey", "chicken", "nuggets", "tapioca", "chocolate", "cake", "soup", "iced", "tea"], "coordinates": [NaN, NaN], "website": "nan", "place_id": "ChIJg2_Pk9Ty_zIRN19Ifc3actI", "reviews": null}, "Lugawan Bulaluhan Restaurant": {"type": "eat", "description": ["batchoy", "p20", "gato", "p30", "lugaw", "p15", "zeki", "p55", "sort", "drinks", "p10"], "coordinates": [NaN, NaN], "website": "nan", "place_id": "ChIJnQrmVtjy_zIR45X27-KYUTc", "reviews": null}, "Brewberry Caf\u00e9": {"type": "drink", "description": ["nan"], "coordinates": [NaN, NaN], "website": "nan", "place_id": "ChIJKRSbVNby_zIRm_ev9oBYo-Y", "reviews": null}, "Kofitricks Caf\u00e9": {"type": "drink", "description": ["coffee", "shop", "pinoy", "indian", "cuisine", "wi", "fi", "zone"], "coordinates": [NaN, NaN], "website": "http://kofitricks.co.cc", "place_id": "ChIJ7XG5z9ny_zIRHcII3SZubPY", "reviews": null}, "Hotel Ramon": {"type": "sleep", "description": ["aircon", "wifi", "laundry", "service"], "coordinates": [NaN, NaN], "website": "nan", "place_id": "ChIJ-20vHijz_zIR7IeWGFt_WY8", "reviews": null}, "Park view Hotel.": {"type": "sleep", "description": ["fan", "double", "rooms", "outside", "bathrooms", "c", "double", "rooms", "outside", "bathrooms", "rooms", "cable", "tv", "phone", "free", "wifi", "pay", "master", "card", "visa", "card"], "coordinates": [NaN, NaN], "website": "nan", "place_id": "ChIJD_8R59fy_zIRxtxlIQLZU3k", "reviews": null}, "Willshire inn": {"type": "sleep", "description": ["economy", "c", "single", "rooms", "bathroom", "cable", "tv", "economy", "c", "double", "rooms", "bathroom", "cable", "tv", "standard", "c", "double", "rooms", "deluxe", "c", "double", "rooms"], "coordinates": [NaN, NaN], "website": "nan", "place_id": "ChIJOdUUu9Dy_zIRIkZhyX3TPzM", "reviews": null}, "Plaza star Business hotel": {"type": "sleep", "description": ["c", "single", "double", "rooms", "hot", "water", "bathrooms", "cable", "tv", "free", "wifi"], "coordinates": [NaN, NaN], "website": "nan", "place_id": "ChIJmzXlHtfy_zIReTfQwkrFJF4", "reviews": null}, "Wills Place Business hotel.": {"type": "sleep", "description": ["economy", "c", "single", "double", "rooms", "hot", "water", "bathrooms", "cable", "tv", "free", "wifi"], "coordinates": [NaN, NaN], "website": "http://www.willsplace.cdoph.com", "place_id": "ChIJk6yP2tny_zIRNKEve_9-a0g", "reviews": null}, "CDO tourist inn": {"type": "sleep", "description": ["fan", "rooms", "12", "hours", "c", "rooms", "12", "hours", "c", "rooms", "24", "hours", "common", "bathrooms", "free", "wifi"], "coordinates": [NaN, NaN], "website": "nan", "place_id": "ChIJr7m6PNny_zIRRbY1DSn6P84", "reviews": null}, "D Santes place Business hotel": {"type": "sleep", "description": ["c", "single", "room", "hot", "water", "bathroom", "cable", "tv", "c", "economy", "double", "room", "hot", "water", "bathroom", "cable", "tv"], "coordinates": [NaN, NaN], "website": "nan", "place_id": "ChIJ_0sGr8Ty_zIRsBjfKGiAs6s", "reviews": null}, "King Lawrences inn": {"type": "sleep", "description": ["c", "rooms", "bathroom", "12", "24", "hours"], "coordinates": [NaN, NaN], "website": "nan", "place_id": "ChIJlyB4Wtjy_zIR7fndGdDwrYI", "reviews": null}, "G V Hotel": {"type": "sleep", "description": ["c", "single", "double", "rooms", "bathrooms", "cable", "tv", "gv", "hotel", "cdo", "102", "rooms"], "coordinates": [NaN, NaN], "website": "http://www.gvhotels.com.ph", "place_id": "ChIJEdi89-fy_zIR0k4nDHq34dY", "reviews": null}, "Jerggys Appartelle Inn": {"type": "sleep", "description": ["c", "double", "rooms", "bathrooms", "cable", "tv", "7", "hours", "12", "hours", "24", "hours"], "coordinates": [NaN, NaN], "website": "nan", "place_id": "ChIJzUajfiTz_zIRwz9fWE4MPXM", "reviews": null}, "Beatrice Inn": {"type": "sleep", "description": ["c", "single", "rooms", "bathroom", "cable", "tv", "c", "double", "rooms", "hot", "water", "bathroom", "cable", "tv", "rooms", "free", "wifi"], "coordinates": [NaN, NaN], "website": "nan", "place_id": "ChIJAYSd7dfy_zIRCg0sDEsrAsQ", "reviews": null}, "Rosarios Place business Hotel.": {"type": "sleep", "description": ["single", "room", "economy", "double", "standard", "double", "de", "luxe", "good", "3", "persons", "rooms", "c", "lcd", "tv", "hot", "water"], "coordinates": [NaN, NaN], "website": "nan", "place_id": "ChIJA3ufGNry_zIRzMtojzgFgWM", "reviews": null}, "King William Inn": {"type": "sleep", "description": ["c", "rooms", "bathrooms", "cable", "tv"], "coordinates": [NaN, NaN], "website": "nan", "place_id": "ChIJMXti49fy_zIRlnUSQfFra78", "reviews": null}, "Mardale Pension House": {"type": "sleep", "description": ["c", "single", "double", "rooms", "hot", "water", "bathroom", "cable", "tv", "wifi", "zone", "standby", "generator", "telephone", "room", "monday", "till", "wednesday", "rooms", "500"], "coordinates": [NaN, NaN], "website": "nan", "place_id": "ChIJfW9LjNby_zIRCgVdOOmdgVA", "reviews": null}, "Budgetel Cagayan de oro": {"type": "sleep", "description": ["16", "18", "bed", "dorm", "c"], "coordinates": [NaN, NaN], "website": "nan", "place_id": "ChIJmfcJkfrs_zIRJ3MOjReKXEg", "reviews": null}, "Dian Stay Inn": {"type": "sleep", "description": ["c", "economy", "double", "bathroom", "cable", "tv", "c", "standard", "double", "bathroom", "cable", "tv"], "coordinates": [NaN, NaN], "website": "nan", "place_id": "ChIJp8x0ktDy_zIRAFIu09cxNt4", "reviews": null}, "Olive Suites": {"type": "sleep", "description": ["c", "single", "double", "rooms", "hot", "water", "bathroom", "cable", "tv", "free", "wifi", "41", "rooms"], "coordinates": [NaN, NaN], "website": "nan", "place_id": "ChIJrRMgstny_zIRmRN0npu0wvg", "reviews": null}, "Three Sisters Dorm and Transient": {"type": "sleep", "description": ["dorm", "beds", "c", "double", "rooms", "bathroom", "cable", "tv", "free", "wifi"], "coordinates": [NaN, NaN], "website": "nan", "place_id": "ChIJdwK2y9ny_zIREU4NZwnPHmQ", "reviews": null}, "Princeton Inn": {"type": "sleep", "description": ["c", "double", "rooms", "bathroom", "cable", "tv"], "coordinates": [NaN, NaN], "website": "nan", "place_id": "ChIJk4Vh4Njy_zIRvvMIN-Y0lGw", "reviews": null}, "Pryce Plaza": {"type": "sleep", "description": ["pryce", "plaza", "located", "cagayan", "de", "oro", "city", "philippines", "offers", "80", "air", "conditioned", "rooms", "suites", "mini", "bar", "cable", "tv", "idd", "phone", "extension", "bathroom", "amenities", "include", "elite", "spa", "fitness", "club", "swimming", "pool", "restaurants", "cafe", "cagayan", "compadres", "bar", "josefina", "seafood", "grill", "japanese", "corner", "staying", "visit", "interesting", "places", "like", "la", "castilla", "museum", "migtugsok", "falls", "macahambus", "hill", "cave"], "coordinates": [NaN, NaN], "website": "http://www.pryceplaza.ph", "place_id": "ChIJtwZ0Ey3z_zIR9N96E2h-CVk", "reviews": null}, "Ridgeview Chalets": {"type": "sleep", "description": ["located", "within", "xavier", "estates", "complex", "every", "room", "air", "conditioning", "pocket", "refrigerator", "mini", "bar", "cable", "tv", "high", "speed", "internet", "access", "amenities", "fitness", "room", "game", "room", "restaurant", "cafe", "bar", "lounge", "outdoor", "swimming", "pool"], "coordinates": [NaN, NaN], "website": "http://www.xavierclub.com.ph", "place_id": "ChIJjxxRPu6M_zIRnwYdSGZ56x4", "reviews": null}, "Seda Centrio": {"type": "sleep", "description": ["rooms", "executive", "work", "desk", "mini", "bar", "coffee", "tea", "making", "facilities", "room", "safe", "restaurant", "lounge", "meeting", "rooms", "gym", "adult", "children", "pool", "room", "massage", "currency", "exchange", "parking", "safety", "deposit", "boxes", "airport", "city", "transfers", "laundry", "dry", "cleaning"], "coordinates": [NaN, NaN], "website": "http://www.sedahotels.com/centrio", "place_id": "ChIJzTY96Nzy_zIRGyVniXo8BKY", "reviews": null}, "Miami Inn": {"type": "sleep", "description": ["vamenta", "blvd", "carmen"], "coordinates": [NaN, NaN], "website": "http://www.miami-inncdo.com", "place_id": "ChIJJVpYMCbz_zIRP0pWbGOI8TE", "reviews": null}, "Philtown Hotel": {"type": "sleep", "description": ["nan"], "coordinates": [NaN, NaN], "website": "http://www.philtownhotel.com", "place_id": "ChIJ_____7-M_zIR8u9is1TVuWg", "reviews": null}, "Kingston Lodge": {"type": "sleep", "description": ["mastersons", "ave", "upper", "carmen", "5", "minutes", "lumbia", "airport", "sits", "adjacent", "pueblo", "de", "oro", "golf", "course", "lies", "opposite", "xavier", "estates", "sports", "country", "club", "phone", "number", "63", "88", "858", "5696", "price", "php", "1", "120", "00"], "coordinates": [NaN, NaN], "website": "http://www.kingstonlodge-cagayandeoro.com/", "place_id": "ChIJcxjVtPKM_zIROGvE5OXrO_I", "reviews": null}, "Gardens of Malasag Eco-Tourism Village": {"type": "sleep", "description": ["unique", "beautiful", "place", "please", "read", "description", "see", "section"], "coordinates": [NaN, NaN], "website": "http://gardensmalasgetv.com", "place_id": "ChIJOXMaCbGS_zIRjSY5Poc_HYg", "reviews": null}, "The Malasag House": {"type": "sleep", "description": ["unique", "philippines", "european", "style", "bed", "breakfast", "relaxing", "stunning", "view"], "coordinates": [NaN, NaN], "website": "http://www.themalasaghouse.com", "place_id": "ChIJoaz2fa-S_zIRGAQv6ig9NJw", "reviews": null}, "De Luxe Hotel": {"type": "sleep", "description": ["capt", "vicente", "roa", "st"], "coordinates": [NaN, NaN], "website": "http://www.deluxehotelcdo.com/", "place_id": "ChIJWQ5JS9Dy_zIRe-QwP0zXOP4", "reviews": null}, "Mallberry Business Suites Hotel": {"type": "sleep", "description": ["florentino", "st", "limketkai", "center"], "coordinates": [NaN, NaN], "website": "http://www.malberrysuites.com", "place_id": "ChIJk8j6wMTy_zIRrQ_lkz06DtU", "reviews": null}}}}