{"Loutraki": {"size": 47, "country": "Greece", "full_desc": ["10", "km", "away", "geraneia", "mountain", "spa", "treatments", "wellness", "sessions", "greek", "style", "pizza", "traditional", "greek", "dishes", "moussaka", "octopus", "salad", "giant", "black", "beans", "onions", "modern", "greek", "cuisine", "live", "music", "venue", "beach", "bar", "club", "theme", "party", "1", "star", "hotel", "built", "2002", "2", "star", "hotel", "renovated", "2004", "2", "star", "hotel", "2", "star", "hotel", "2", "star", "hotel", "rooms", "let", "2", "star", "hotel", "2", "star", "hotel", "2", "star", "hotel", "2", "star", "hotel", "2", "star", "hotel", "2", "star", "hotel", "2", "star", "hotel", "2", "star", "hotel", "built", "1936", "renovated", "2004", "36", "c", "rooms", "bath", "shower", "wi", "fi", "wireless", "internet", "satellite", "tv", "2", "star", "hotel", "2", "star", "hotel", "2", "star", "hotel", "2", "star", "hotel", "2", "star", "hotel", "3", "star", "hotel", "3", "star", "hotel", "3", "star", "hotel", "3", "star", "hotel", "3", "star", "hotel", "3", "star", "hotel", "3", "star", "hotel", "3", "star", "hotel", "5", "star", "hotel", "built", "2002", "renovated", "2006", "5", "star", "hotel", "4", "star", "hotel", "4", "star", "hotel", "4", "star", "hotel"], "attractions": {"Folk Museum": {"type": "see", "description": ["nan"], "coordinates": [37.9779, 22.9776], "website": "nan", "place_id": null, "reviews": null, "purpose": [], "cost": ""}, "Monastery Osios Patapios": {"type": "see", "description": ["10", "km", "away", "geraneia", "mountain"], "coordinates": [37.995932, 22.9769], "website": "nan", "place_id": null, "reviews": null, "purpose": [], "cost": ""}, "The Diolkos and the Corinth Canal": {"type": "see", "description": ["nan"], "coordinates": [NaN, NaN], "website": "nan", "place_id": null, "reviews": null, "purpose": [], "cost": ""}, "Vouliagmeni Lake": {"type": "see", "description": ["nan"], "coordinates": [38.0292, 22.8823], "website": "nan", "place_id": null, "reviews": null, "purpose": [], "cost": ""}, "Temple of Hera": {"type": "see", "description": ["nan"], "coordinates": [NaN, NaN], "website": "nan", "place_id": null, "reviews": null, "purpose": [], "cost": ""}, "Loutraki Thermal Spa": {"type": "do", "description": ["spa", "treatments", "wellness", "sessions"], "coordinates": [37.9805, 22.9748], "website": "http://www.loutrakispa.gr", "place_id": null, "reviews": null, "purpose": [], "cost": ""}, "Di Giorgio": {"type": "eat", "description": ["greek", "style", "pizza"], "coordinates": [37.97602, 22.97699], "website": "https://www.facebook.com/digiorgio.gr", "place_id": null, "reviews": null, "purpose": [], "cost": ""}, "Agios Efrosinos": {"type": "eat", "description": ["traditional", "greek", "dishes", "moussaka", "octopus", "salad", "giant", "black", "beans", "onions"], "coordinates": [37.97848, 22.97842], "website": "http://www.agiosefrosinos.gr", "place_id": null, "reviews": null, "purpose": [], "cost": ""}, "Rigani Restaurant": {"type": "eat", "description": ["modern", "greek", "cuisine"], "coordinates": [37.97464, 22.97684], "website": "http://www.rigani.gr", "place_id": null, "reviews": null, "purpose": [], "cost": ""}, "Prima Vista Live": {"type": "drink", "description": ["live", "music", "venue"], "coordinates": [37.9643, 22.9787], "website": "nan", "place_id": null, "reviews": null, "purpose": ["friends", "spring break"], "cost": ""}, "Waves": {"type": "drink", "description": ["beach", "bar"], "coordinates": [37.9576, 22.9688], "website": "https://www.facebook.com/wavesloutraki/", "place_id": "ChIJk_Lm-ky0bTkREisUnBRtZ_4", "reviews": null, "purpose": ["friends", "spring break"], "cost": ""}, "Alterra": {"type": "drink", "description": ["club", "theme", "party"], "coordinates": [37.9569, 22.9668], "website": "https://www.facebook.com/alterraloutraki/", "place_id": null, "reviews": null, "purpose": ["spring break"], "cost": ""}, "Alkioni Campsite": {"type": "sleep", "description": ["nan"], "coordinates": [NaN, NaN], "website": "http://www.campingalkioni.gr/", "place_id": null, "reviews": null, "purpose": [], "cost": ""}, "Hotel M": {"type": "sleep", "description": ["1", "star", "hotel", "built", "2002"], "coordinates": [37.9639, 22.9778], "website": "http://www.hotelm.gr/", "place_id": null, "reviews": null, "purpose": ["educational"], "cost": ""}, "Ekonomion Hotel": {"type": "sleep", "description": ["nan"], "coordinates": [NaN, NaN], "website": "nan", "place_id": null, "reviews": null, "purpose": [], "cost": ""}, "Mitzithras Hotel": {"type": "sleep", "description": ["2", "star", "hotel", "renovated", "2004"], "coordinates": [37.9757, 22.9777], "website": "http://www.mitzithras.gr", "place_id": null, "reviews": null, "purpose": [], "cost": ""}, "Mantas Seaside Boutique Hotel": {"type": "sleep", "description": ["2", "star", "hotel"], "coordinates": [37.9728, 22.9774], "website": "http://mantashotels.gr/gr/boutique.php", "place_id": null, "reviews": null, "purpose": [], "cost": ""}, "Akti Loutraki Hotel": {"type": "sleep", "description": ["2", "star", "hotel"], "coordinates": [37.9789, 22.9768], "website": "nan", "place_id": null, "reviews": null, "purpose": [], "cost": ""}, "Galanopoulos Hotel": {"type": "sleep", "description": ["2", "star", "hotel"], "coordinates": [37.981147, 22.973616], "website": "http://www.galanopoulos-hotel.com {{dead link|May 2016}}", "place_id": null, "reviews": null, "purpose": [], "cost": ""}, "Hotel Segas": {"type": "sleep", "description": ["nan"], "coordinates": [37.9785, 22.9782], "website": "http://www.hotelsegas.com", "place_id": null, "reviews": null, "purpose": [], "cost": ""}, "Diolkos Studios": {"type": "sleep", "description": ["rooms", "let"], "coordinates": [37.9635, 22.9701], "website": "http://diolkos-studios.gr", "place_id": null, "reviews": null, "purpose": [], "cost": ""}, "Bretagne Hotel": {"type": "sleep", "description": ["2", "star", "hotel"], "coordinates": [37.9788, 22.9771], "website": "nan", "place_id": null, "reviews": null, "purpose": [], "cost": ""}, "Belle Vue Hotel": {"type": "sleep", "description": ["2", "star", "hotel"], "coordinates": [37.9753, 22.9777], "website": "http://www.bellevue-loutraki.gr", "place_id": null, "reviews": null, "purpose": [], "cost": ""}, "Loutraki Hotel": {"type": "sleep", "description": ["2", "star", "hotel"], "coordinates": [37.9765, 22.9776], "website": "nan", "place_id": null, "reviews": null, "purpose": [], "cost": ""}, "Marion Hotel": {"type": "sleep", "description": ["2", "star", "hotel"], "coordinates": [37.9816, 22.9731], "website": "http://www.marionloutraki.com", "place_id": null, "reviews": null, "purpose": [], "cost": ""}, "Isthmia Central Hotel": {"type": "sleep", "description": ["2", "star", "hotel"], "coordinates": [37.9755, 22.9777], "website": "http://mantashotels.gr", "place_id": null, "reviews": null, "purpose": [], "cost": ""}, "Cristina Maris Hotel": {"type": "sleep", "description": ["2", "star", "hotel"], "coordinates": [37.9669, 22.9726], "website": "http://www.hotel-cristina-maris.gr", "place_id": null, "reviews": null, "purpose": [], "cost": ""}, "Petit Palais Hotel": {"type": "sleep", "description": ["2", "star", "hotel"], "coordinates": [37.9819, 22.9726], "website": "http://www.petitpalais.gr", "place_id": null, "reviews": null, "purpose": [], "cost": ""}, "Kosmopolit Hotel": {"type": "sleep", "description": ["2", "star", "hotel", "built", "1936", "renovated", "2004", "36", "c", "rooms", "bath", "shower", "wi", "fi", "wireless", "internet", "satellite", "tv"], "coordinates": [37.9782, 22.978], "website": "http://www.kosmopolit.gr", "place_id": null, "reviews": null, "purpose": ["educational"], "cost": ""}, "Andreou Hotel": {"type": "sleep", "description": ["2", "star", "hotel"], "coordinates": [37.979, 22.9769], "website": "nan", "place_id": null, "reviews": null, "purpose": [], "cost": ""}, "Galaxy Hotel": {"type": "sleep", "description": ["2", "star", "hotel"], "coordinates": [37.9852, 22.9623], "website": "http://www.hotel-galaxy.net", "place_id": null, "reviews": null, "purpose": [], "cost": ""}, "Marko Hotel": {"type": "sleep", "description": ["2", "star", "hotel"], "coordinates": [37.975, 22.9767], "website": "nan", "place_id": null, "reviews": null, "purpose": [], "cost": ""}, "Ilion Hotel": {"type": "sleep", "description": ["2", "star", "hotel"], "coordinates": [37.9715, 22.9781], "website": "http://www.ilionhotel.com", "place_id": null, "reviews": null, "purpose": [], "cost": ""}, "Mon Repos Hotel": {"type": "sleep", "description": ["2", "star", "hotel"], "coordinates": [NaN, NaN], "website": "nan", "place_id": null, "reviews": null, "purpose": [], "cost": ""}, "Aegli Hotel": {"type": "sleep", "description": ["3", "star", "hotel"], "coordinates": [37.9804, 22.9741], "website": "http://www.hotel-egli.gr", "place_id": null, "reviews": null, "purpose": [], "cost": ""}, "Barbara Hotel": {"type": "sleep", "description": ["3", "star", "hotel"], "coordinates": [37.9592, 22.9676], "website": "http://www.hotel-barbara-loutraki-greece.com/", "place_id": null, "reviews": null, "purpose": [], "cost": ""}, "Pappas Hotel": {"type": "sleep", "description": ["3", "star", "hotel"], "coordinates": [37.986489, 22.956961], "website": "http://www.hotelpappas.gr", "place_id": null, "reviews": null, "purpose": [], "cost": ""}, "Vassilikon Hotel": {"type": "sleep", "description": ["3", "star", "hotel"], "coordinates": [37.9783, 22.9776], "website": "http://www.vassilikonhotel.gr", "place_id": null, "reviews": null, "purpose": [], "cost": ""}, "Kontis Hotel": {"type": "sleep", "description": ["3", "star", "hotel"], "coordinates": [NaN, NaN], "website": "nan", "place_id": null, "reviews": null, "purpose": [], "cost": ""}, "Excelsior Hotel": {"type": "sleep", "description": ["3", "star", "hotel"], "coordinates": [37.978, 22.9769], "website": "http://www.excelsior-gr.com", "place_id": "ChIJR-SvZTkbdkgRZZt4kLYqeNY", "reviews": null, "purpose": [], "cost": ""}, "Theoxenia Hotel": {"type": "sleep", "description": ["3", "star", "hotel"], "coordinates": [37.9804, 22.9739], "website": "http://www.hoteltheoxenia.com", "place_id": null, "reviews": null, "purpose": [], "cost": ""}, "Bakos Hotel": {"type": "sleep", "description": ["3", "star", "hotel"], "coordinates": [37.9726, 22.9769], "website": "http://www.hotelbakos.gr", "place_id": null, "reviews": null, "purpose": [], "cost": ""}, "Club Hotel Casino Loutraki": {"type": "sleep", "description": ["5", "star", "hotel", "built", "2002", "renovated", "2006"], "coordinates": [37.961, 22.9696], "website": "http://www.clubhotelloutraki.gr", "place_id": null, "reviews": null, "purpose": ["educational"], "cost": ""}, "Poseidon Resort Hotel": {"type": "sleep", "description": ["5", "star", "hotel"], "coordinates": [37.9949, 22.9482], "website": "http://www.poseidonresort.gr", "place_id": null, "reviews": null, "purpose": [], "cost": ""}, "Paolo Hotel": {"type": "sleep", "description": ["4", "star", "hotel"], "coordinates": [37.973849, 22.976428], "website": "http://hotelpaolo.gr", "place_id": null, "reviews": null, "purpose": [], "cost": ""}, "Park Hotel": {"type": "sleep", "description": ["4", "star", "hotel"], "coordinates": [37.9793, 22.9763], "website": "http://www.hotelpark.com.gr", "place_id": "ChIJOVx45rAcshQR8eTTQdV_VRE", "reviews": null, "purpose": [], "cost": ""}, "Achillion Hotel": {"type": "sleep", "description": ["4", "star", "hotel"], "coordinates": [37.9766, 22.9771], "website": "http://www.achillion-loutraki.gr", "place_id": null, "reviews": null, "purpose": [], "cost": ""}}, "coordinates": ["37.9779", "22.9776"]}}