{"Newark (New Jersey)": {"size": 58, "country": "United States", "full_desc": ["branch", "brook", "park", "contains", "360", "acres", "open", "meadowland", "small", "patches", "woodland", "gently", "rolling", "terrain", "4", "100", "cherry", "trees", "blossom", "april", "greater", "variety", "number", "famed", "trees", "washington", "c", "park", "1", "7", "miles", "downtown", "accessible", "light", "rail", "includes", "spectacular", "views", "cathedral", "basilica", "sacred", "heart", "cathedral", "basilica", "sacred", "heart", "french", "gothic", "styled", "cathedral", "fourth", "largest", "north", "america", "boasting", "upwards", "200", "stained", "glass", "windows", "14", "giant", "bells", "cast", "italy", "cathedral", "hosts", "number", "symphony", "orchestras", "concerts", "addition", "serving", "mother", "church", "roman", "catholic", "archdiocese", "newark", "north", "downtown", "newark", "across", "branch", "brook", "park", "accessible", "light", "rail", "park", "downtown", "originally", "militia", "training", "green", "1600s", "wars", "america", "monument", "imposing", "work", "mount", "rushmore", "artist", "gutzon", "borglum", "summer", "thursdays", "park", "hosts", "common", "greens", "farmers", "market", "museum", "complex", "incorporates", "80", "galleries", "art", "science", "mini", "zoo", "planetarium", "cafe", "auditorium", "sculpture", "garden", "schoolhouse", "ballantine", "house", "restored", "1885", "mansion", "national", "historic", "landmark", "big", "park", "plus", "golf", "course", "large", "lake", "designed", "olmsted", "brothers", "addition", "hosting", "devils", "seton", "hall", "university", "basketball", "games", "new", "jersey", "ironmen", "misl", "indoor", "soccer", "games", "held", "center", "concerts", "w", "f", "noon", "6pm", "sa", "11am", "4pm", "described", "new", "york", "times", "feisty", "alternative", "art", "space", "newark", "often", "shows", "artwork", "razor", "sharp", "social", "political", "edge", "w", "f", "noon", "6pm", "sa", "1pm", "6pm", "contemporary", "art", "gallery", "th", "sa", "noon", "6pm", "contemporary", "art", "gallery", "contemporary", "art", "gallery", "cuban", "cultural", "center", "contemporary", "art", "gallery", "friday", "night", "sunday", "brunch", "jazz", "series", "1", "depot", "square", "montclair", "madison", "west", "orange", "nj", "great", "facility", "explore", "pick", "book", "learn", "little", "something", "city", "classic", "diner", "great", "prices", "east", "indian", "fast", "food", "edison", "place", "pru", "center", "plain", "designer", "burgers", "etc", "market", "street", "pru", "center", "breakfast", "lunch", "closes", "7", "30pm", "great", "southern", "bbq", "soul", "food", "pru", "center", "broad", "street", "amazing", "latin", "food", "corner", "ferry", "niagara", "st", "restaurant", "one", "best", "portuguese", "restaurants", "ironbound", "district", "newark", "give", "large", "portions", "best", "sangria", "neighborhood", "delicious", "fish", "drinks", "lunch", "dinner", "ironbound", "night", "drinks", "tel", "courteous", "clean", "convenient", "ayor", "bargain", "coming", "historic", "district", "harrison", "path", "station", "across", "river", "downtown", "newark", "riverwalk", "clay", "street", "bridge", "recently", "renovated", "runs", "free", "guest", "shuttles", "newark", "penn", "station", "well", "newark", "airport", "rooms", "back", "views", "manhattan", "front", "views", "military", "park", "broad", "street", "relatively", "safe", "downtown", "street", "njpac", "across", "street", "route", "1", "9", "frontage", "road", "618", "routes", "1", "9", "frontage", "road", "walking", "distance", "terminals", "conveient", "transportation", "652", "route", "1", "9", "frontage", "road"], "attractions": {"Branch Brook Park": {"type": "see", "description": ["branch", "brook", "park", "contains", "360", "acres", "open", "meadowland", "small", "patches", "woodland", "gently", "rolling", "terrain", "4", "100", "cherry", "trees", "blossom", "april", "greater", "variety", "number", "famed", "trees", "washington", "c", "park", "1", "7", "miles", "downtown", "accessible", "light", "rail", "includes", "spectacular", "views", "cathedral", "basilica", "sacred", "heart"], "coordinates": [40.770278000000005, -74.176389], "website": "http://www.essex-countynj.org/p/index.php?section=parks/sites/bb&ImgLoc=images/branch", "place_id": "ChIJc1AL0JFUwokR_0VAlpgIh80", "reviews": null, "purpose": [], "cost": ""}, "Cathedral Basilica of the Sacred Heart": {"type": "see", "description": ["cathedral", "basilica", "sacred", "heart", "french", "gothic", "styled", "cathedral", "fourth", "largest", "north", "america", "boasting", "upwards", "200", "stained", "glass", "windows", "14", "giant", "bells", "cast", "italy", "cathedral", "hosts", "number", "symphony", "orchestras", "concerts", "addition", "serving", "mother", "church", "roman", "catholic", "archdiocese", "newark", "north", "downtown", "newark", "across", "branch", "brook", "park", "accessible", "light", "rail"], "coordinates": [40.7549, -74.1784], "website": "http://www.cathedralbasilica.org/", "place_id": "ChIJ47I5545UwokRn3HFwajIdbc", "reviews": null, "purpose": ["friends", "spring break"], "cost": ""}, "Military Park": {"type": "see", "description": ["park", "downtown", "originally", "militia", "training", "green", "1600s", "wars", "america", "monument", "imposing", "work", "mount", "rushmore", "artist", "gutzon", "borglum", "summer", "thursdays", "park", "hosts", "common", "greens", "farmers", "market"], "coordinates": [40.739632, -74.169134], "website": "nan", "place_id": "ChIJdxGhsYFTwokRdZS8Ea6Io1g", "reviews": null, "purpose": ["educational"], "cost": ""}, "Newark Museum": {"type": "see", "description": ["museum", "complex", "incorporates", "80", "galleries", "art", "science", "mini", "zoo", "planetarium", "cafe", "auditorium", "sculpture", "garden", "schoolhouse", "ballantine", "house", "restored", "1885", "mansion", "national", "historic", "landmark"], "coordinates": [40.742965000000005, -74.171653], "website": "http://www.newarkmuseum.org", "place_id": "ChIJ5fsDD4BUwokRxwsQqWQjEMM", "reviews": null, "purpose": ["educational", "family"], "cost": ""}, "Weequahic Park": {"type": "see", "description": ["big", "park", "plus", "golf", "course", "large", "lake", "designed", "olmsted", "brothers"], "coordinates": [40.702, -74.203], "website": "http://www.essex-countynj.org/p/index.php?section=parks/sites/we", "place_id": "ChIJkYSSL9pSwokRoFvmDefIH1Y", "reviews": null, "purpose": [], "cost": ""}, "Aljira: A Center for Contemporary Art": {"type": "do", "description": ["w", "f", "noon", "6pm", "sa", "11am", "4pm", "described", "new", "york", "times", "feisty", "alternative", "art", "space", "newark", "often", "shows", "artwork", "razor", "sharp", "social", "political", "edge"], "coordinates": [NaN, NaN], "website": "http://www.aljira.org", "place_id": "ChIJYyVmbIBTwokRwJgiLWXkKaA", "reviews": null, "purpose": ["educational"], "cost": ""}, "City Without Walls": {"type": "do", "description": ["w", "f", "noon", "6pm", "sa", "1pm", "6pm", "contemporary", "art", "gallery"], "coordinates": [NaN, NaN], "website": "http://www.cwow.org", "place_id": "ChIJcwcE3HNTwokR5J1cAgMM73I", "reviews": null, "purpose": ["educational"], "cost": ""}, "Gallery Aferro": {"type": "do", "description": ["th", "sa", "noon", "6pm", "contemporary", "art", "gallery"], "coordinates": [NaN, NaN], "website": "http://www.aferro.org", "place_id": "ChIJM1yPQnlTwokRcdDgLuuu6Lc", "reviews": null, "purpose": ["educational"], "cost": ""}, "Gallery Twenty-One": {"type": "do", "description": ["contemporary", "art", "gallery", "cuban", "cultural", "center"], "coordinates": [NaN, NaN], "website": "http://www.gallerytwenty-one.com {{dead link|May 2016}}", "place_id": "ChIJk4azM7FVwokRZrfj6t_k6iE", "reviews": null, "purpose": ["educational"], "cost": ""}, "Red Saw Gallery": {"type": "do", "description": ["contemporary", "art", "gallery"], "coordinates": [NaN, NaN], "website": "http://www.redsawart.com/wb/ {{dead link|May 2016}}", "place_id": "not found", "reviews": null, "purpose": ["educational"], "cost": ""}, "The Priory": {"type": "do", "description": ["friday", "night", "sunday", "brunch", "jazz", "series"], "coordinates": [NaN, NaN], "website": "nan", "place_id": "ChIJA7m8Z2JTwokRyMJoK_Q9uVQ", "reviews": null, "purpose": [], "cost": ""}, "Trumpets Jazz Club and Restaurant": {"type": "do", "description": ["1", "depot", "square", "montclair"], "coordinates": [NaN, NaN], "website": "http://www.trumpetsjazz.com", "place_id": "ChIJMQ6y4FFVwokRKT2M9zZFmaU", "reviews": null, "purpose": [], "cost": ""}, "Shanghai Jazz": {"type": "do", "description": ["madison"], "coordinates": [NaN, NaN], "website": "http://www.shanghaijazz.com", "place_id": "ChIJe2R_73BTwokRuUQbHK5ZQtU", "reviews": null, "purpose": [], "cost": ""}, "Cecil's Jazz Club & Restaurant": {"type": "do", "description": ["west", "orange", "nj"], "coordinates": [NaN, NaN], "website": "http://www.cecilsjazzclub.com", "place_id": "ChIJ38jfXRH2wokR3ZewiTRd9oU", "reviews": null, "purpose": [], "cost": ""}, "Greater Abyssinian Baptist Church": {"type": "do", "description": ["nan"], "coordinates": [NaN, NaN], "website": "http://www.greaterabyssinian.org", "place_id": "ChIJY2uSK9ZSwokRaG_8EznLSyI", "reviews": null, "purpose": [], "cost": ""}, "New Hope Baptist Chuirch": {"type": "do", "description": ["nan"], "coordinates": [NaN, NaN], "website": "http://www.newhopenewark.org", "place_id": "ChIJmUfBCINUwokRwtW0fNgEgew", "reviews": null, "purpose": [], "cost": ""}, "Newark Gospel Tabernacle": {"type": "do", "description": ["nan"], "coordinates": [NaN, NaN], "website": "http://www.newarktab.org/Groups/1000058048 {{dead link|May 2016}}", "place_id": "ChIJxSIbmKisw4kRkZ0jPzK_K2E", "reviews": null, "purpose": [], "cost": ""}, "Duke's Southern Table": {"type": "do", "description": ["nan"], "coordinates": [NaN, NaN], "website": "http://dukesnewark.com/contact-us/", "place_id": "ChIJ3wQcUG5TwokRC8OSKG30Awk", "reviews": null, "purpose": [], "cost": ""}, "Central Restaurant": {"type": "eat", "description": ["classic", "diner", "great", "prices"], "coordinates": [40.74175, -74.17053], "website": "nan", "place_id": "ChIJIXpTAYBTwokR2GW29vzOIlo", "reviews": null, "purpose": [], "cost": ""}, "Mi Gente Cafe": {"type": "eat", "description": ["nan"], "coordinates": [NaN, NaN], "website": "nan", "place_id": "ChIJlSKpDIBTwokRgjeLJ6cX7qo", "reviews": null, "purpose": [], "cost": ""}, "Ferry Street Barbeque": {"type": "eat", "description": ["nan"], "coordinates": [40.731, -74.16152], "website": "nan", "place_id": "ChIJ4XmMMoVTwokRuvhiMRkWH7M", "reviews": null, "purpose": [], "cost": ""}, "Cafe Caffe Gourmet": {"type": "eat", "description": ["nan"], "coordinates": [NaN, NaN], "website": "nan", "place_id": "ChIJsXShiHdTwokR9HuKFY1nTx0", "reviews": null, "purpose": [], "cost": ""}, "Spice & Grill": {"type": "eat", "description": ["east", "indian", "fast", "food"], "coordinates": [40.7375, -74.1725], "website": "https://www.spicengrillofnewark.com", "place_id": "not found", "reviews": null, "purpose": [], "cost": ""}, "Boi Na Brasa": {"type": "eat", "description": ["nan"], "coordinates": [NaN, NaN], "website": "nan", "place_id": "ChIJc2z7p1qQ9pQRoacvnf30480", "reviews": null, "purpose": [], "cost": ""}, "Brasilia Grille": {"type": "eat", "description": ["nan"], "coordinates": [NaN, NaN], "website": "http://www.brasiliagrill.com", "place_id": "ChIJRy6TmZpTwokRC-bWz-GxF0s", "reviews": null, "purpose": [], "cost": ""}, "Brick City Bar and Grill": {"type": "eat", "description": ["edison", "place", "pru", "center"], "coordinates": [NaN, NaN], "website": "http://www.brickcitybarandgrill.com", "place_id": "ChIJOcvuEHlTwokRnUkSsITomBw", "reviews": null, "purpose": [], "cost": ""}, "Brazilian Bakery": {"type": "eat", "description": ["nan"], "coordinates": [NaN, NaN], "website": "nan", "place_id": "ChIJMxYHXo1TwokRdHsVVlRzBgM", "reviews": null, "purpose": [], "cost": ""}, "Burg": {"type": "eat", "description": ["plain", "designer", "burgers", "etc"], "coordinates": [NaN, NaN], "website": "http://www.burgnj.com", "place_id": "ChIJdxGhsYFTwokRdZS8Ea6Io1g", "reviews": null, "purpose": [], "cost": ""}, "Dinosaur BBQ": {"type": "eat", "description": ["market", "street", "pru", "center"], "coordinates": [NaN, NaN], "website": "http://www.dinosaurbarbque.com/locations/newark/ {{dead link|May 2016}}", "place_id": "ChIJUf4zY4JTwokRSw5EkApChZc", "reviews": null, "purpose": [], "cost": ""}, "Edison House": {"type": "eat", "description": ["nan"], "coordinates": [NaN, NaN], "website": "http://www.edisonalehouse.com/Welcome.html {{dead link|May 2016}}", "place_id": "ChIJRewyhIJTwokRbHjSw8Fkq1U", "reviews": null, "purpose": [], "cost": ""}, "Harvest Table": {"type": "eat", "description": ["breakfast", "lunch"], "coordinates": [NaN, NaN], "website": "nan", "place_id": "ChIJN2KsOX9TwokRwADdpTXFxio", "reviews": null, "purpose": [], "cost": ""}, "Je's Restaurant": {"type": "eat", "description": ["closes", "7", "30pm", "great", "southern", "bbq", "soul", "food"], "coordinates": [NaN, NaN], "website": "http://www.jesrestaurant.com", "place_id": "ChIJf66Kw3lTwokRAyyyFDF8-mU", "reviews": null, "purpose": [], "cost": ""}, "Loft 47": {"type": "eat", "description": ["pru", "center"], "coordinates": [NaN, NaN], "website": "http://www.loft47bistro.com {{dead link|May 2016}}", "place_id": "ChIJHxMMQJ1TwokROSIsa3MuXeU", "reviews": null, "purpose": [], "cost": ""}, "Martini 494": {"type": "eat", "description": ["broad", "street"], "coordinates": [NaN, NaN], "website": "http://www.martini494bistro.com", "place_id": "ChIJ35z8SH5UwokRlFpdmms6Umc", "reviews": null, "purpose": [], "cost": ""}, "Sabor Latino Restaurant": {"type": "eat", "description": ["amazing", "latin", "food"], "coordinates": [NaN, NaN], "website": "nan", "place_id": "ChIJtzRnqZFTwokReD3bZZ5qp-I", "reviews": null, "purpose": [], "cost": ""}, "Seabra's Rodizio": {"type": "eat", "description": ["nan"], "coordinates": [NaN, NaN], "website": "nan", "place_id": "ChIJJZVhLJ9TwokRZ9Em-I_XBPc", "reviews": null, "purpose": [], "cost": ""}, "Sol-Mar Marisqueira & Restaurant": {"type": "eat", "description": ["corner", "ferry", "niagara", "st", "restaurant", "one", "best", "portuguese", "restaurants", "ironbound", "district", "newark", "give", "large", "portions", "best", "sangria", "neighborhood", "delicious", "fish"], "coordinates": [NaN, NaN], "website": "http://solmar-restaurant.com", "place_id": "ChIJYYPgF5JTwokRrnfkEZghZAo", "reviews": null, "purpose": ["friends"], "cost": ""}, "27 Mix": {"type": "eat", "description": ["drinks", "lunch", "dinner"], "coordinates": [NaN, NaN], "website": "http://www.27mix.com", "place_id": "ChIJiwTZAoBTwokRRIiO2kXSn8A", "reviews": null, "purpose": [], "cost": ""}, "Iberia": {"type": "eat", "description": ["nan"], "coordinates": [NaN, NaN], "website": "nan", "place_id": "ChIJMf5cL4VTwokRR7eVY2V37ew", "reviews": null, "purpose": [], "cost": ""}, "Iberia Peninsula": {"type": "eat", "description": ["nan"], "coordinates": [NaN, NaN], "website": "nan", "place_id": "ChIJ_cVR3IRTwokRp-niYR9Xii4", "reviews": null, "purpose": [], "cost": ""}, "Fornos of Spain": {"type": "eat", "description": ["nan"], "coordinates": [NaN, NaN], "website": "nan", "place_id": "ChIJje33wYRTwokRmAFvLzMdyrQ", "reviews": null, "purpose": [], "cost": ""}, "Spanish Tavern": {"type": "eat", "description": ["nan"], "coordinates": [NaN, NaN], "website": "nan", "place_id": "ChIJrw4x8pxTwokRmkY6108JyKA", "reviews": null, "purpose": [], "cost": ""}, "Fernandes Steak House": {"type": "eat", "description": ["nan"], "coordinates": [NaN, NaN], "website": "nan", "place_id": "ChIJ7_PSMfFTwokR1XpvQvUgYUM", "reviews": null, "purpose": [], "cost": ""}, "Spain": {"type": "eat", "description": ["nan"], "coordinates": [NaN, NaN], "website": "nan", "place_id": "ChIJRZT48dOKpRIRwBwqjpJjxbg", "reviews": null, "purpose": [], "cost": ""}, "Blitz Sports Bar": {"type": "drink", "description": ["ironbound"], "coordinates": [NaN, NaN], "website": "http://www.blitzsportsbar.com", "place_id": "ChIJ-ROe95RTwokRWc5w7SrP0Cs", "reviews": null, "purpose": [], "cost": ""}, "Key Club": {"type": "drink", "description": ["night", "drinks"], "coordinates": [NaN, NaN], "website": "http://58parkplacenj.com {{dead link|May 2016}}", "place_id": "ChIJjZ3fuoFTwokRykBZDqBCaCA", "reviews": null, "purpose": [], "cost": ""}, "Newark YMCA": {"type": "sleep", "description": ["tel", "courteous", "clean", "convenient"], "coordinates": [NaN, NaN], "website": "http://www.newarkymca.org/lodging.cfm {{dead link|May 2016}}", "place_id": "ChIJmz2OdoBTwokRVecEvyZrgRc", "reviews": null, "purpose": [], "cost": ""}, "Hotel Riveria": {"type": "sleep", "description": ["ayor", "bargain", "coming", "historic", "district"], "coordinates": [NaN, NaN], "website": "http://hotelrivieranj.com", "place_id": "ChIJu-XHNG1TwokR9TOqI2TMSSY", "reviews": null, "purpose": ["educational"], "cost": "low"}, "Comfort Suites": {"type": "sleep", "description": ["nan"], "coordinates": [NaN, NaN], "website": "nan", "place_id": "ChIJJSyMR78xxIkRehy75NRdic8", "reviews": null, "purpose": [], "cost": ""}, "Element Harrison Newark": {"type": "sleep", "description": ["harrison", "path", "station", "across", "river", "downtown"], "coordinates": [NaN, NaN], "website": "nan", "place_id": "ChIJnQgBKXZUwokRQq5RcYVGOho", "reviews": null, "purpose": [], "cost": ""}, "Hampton Suites": {"type": "sleep", "description": ["newark", "riverwalk", "clay", "street", "bridge"], "coordinates": [NaN, NaN], "website": "http://www.hamptoninnandsuitesnewark.com/reservations.php {{dead link|May 2016}}", "place_id": "ChIJQXD6V3lUwokRQFciKD7tfd4", "reviews": null, "purpose": [], "cost": ""}, "Robert Treat Hotel": {"type": "sleep", "description": ["recently", "renovated", "runs", "free", "guest", "shuttles", "newark", "penn", "station", "well", "newark", "airport", "rooms", "back", "views", "manhattan", "front", "views", "military", "park", "broad", "street", "relatively", "safe", "downtown", "street", "njpac", "across", "street"], "coordinates": [NaN, NaN], "website": "http://www.rthotel.com/", "place_id": "ChIJUXGTrYFTwokR-vIkXDNfduQ", "reviews": null, "purpose": [], "cost": "low"}, "Courtyard Newark Liberty International Airport": {"type": "sleep", "description": ["route", "1", "9", "frontage", "road"], "coordinates": [NaN, NaN], "website": "http://marriott.com/property/propertypage/EWRCA", "place_id": "ChIJ82t4PwdTwokR67rjZndoibw", "reviews": null, "purpose": [], "cost": ""}, "Best Western Newark Airport West": {"type": "sleep", "description": ["nan"], "coordinates": [NaN, NaN], "website": "http://www.bwnewark.com", "place_id": "ChIJOSlAfh1TwokRk06ueEQUhGo", "reviews": null, "purpose": [], "cost": ""}, "Fairfield Inn & Suites Newark Liberty International Airport": {"type": "sleep", "description": ["618", "routes", "1", "9", "frontage", "road"], "coordinates": [NaN, NaN], "website": "http://marriott.com/property/propertypage/EWRFS", "place_id": "not found", "reviews": null, "purpose": [], "cost": ""}, "Holiday Inn": {"type": "sleep", "description": ["nan"], "coordinates": [NaN, NaN], "website": "http://www.ichotelsgroup.com/h/d/hi/1/en/hd/ewria", "place_id": "ChIJGbfM_F9b34cRcJfbMuOuoFY", "reviews": null, "purpose": [], "cost": ""}, "Newark Liberty International Airport Marriott": {"type": "sleep", "description": ["walking", "distance", "terminals", "conveient", "transportation"], "coordinates": [NaN, NaN], "website": "http://marriott.com/property/propertypage/EWRAP", "place_id": "ChIJlXycOvpSwokRRtWN6t7gjJw", "reviews": null, "purpose": [], "cost": ""}, "SpringHill Suites Newark Liberty International Airport": {"type": "sleep", "description": ["652", "route", "1", "9", "frontage", "road"], "coordinates": [NaN, NaN], "website": "http://marriott.com/property/propertypage/EWRSA", "place_id": "ChIJhUTXyKlTwokRe-fp12DescY", "reviews": null, "purpose": [], "cost": ""}}, "coordinates": ["40.770278", "-74.176389"]}}