{"Radom": {"size": 71, "country": "Poland", "full_desc": ["corner", "malczewskiego", "kelles", "krauza", "streets", "polish", "gallery", "faculty", "arts", "technical", "university", "radom", "located", "19th", "century", "toll", "house", "building", "entry", "city", "used", "polish", "polish", "centre", "contemporary", "art", "temporarily", "moved", "away", "location", "ul", "kopernika", "1", "time", "renovation", "rynek", "4", "5", "museum", "contemporary", "arts", "established", "1990", "first", "contemporary", "arts", "dedicated", "museum", "poland", "boasts", "collection", "3", "500", "exhibits", "polish", "open", "air", "museum", "radom", "region", "country", "side", "great", "place", "weekend", "visit", "try", "get", "one", "numerous", "events", "organize", "polish", "one", "unique", "sights", "radom", "founded", "1468", "one", "oldest", "bernardine", "monasteries", "world", "polish", "neo", "gothic", "church", "build", "1905", "polish", "radom", "cathedral", "build", "1898", "1918", "polish", "polish", "one", "oldest", "churches", "radom", "originally", "founded", "1360", "king", "casimir", "great", "sure", "see", "17th", "century", "chapel", "founded", "jan", "kochanowski", "plac", "konstytucji", "3", "maja", "1", "originally", "built", "1902", "eastern", "orthodox", "church", "serves", "roman", "catholic", "military", "church", "polish", "oldest", "remaining", "building", "city", "likely", "build", "1216", "go", "performance", "city", "renowned", "chamber", "orchestra", "see", "theatre", "play", "jan", "kochanowski", "popular", "theatre", "radom", "city", "annual", "festivity", "taking", "place", "around", "middle", "june", "expect", "large", "number", "concerts", "performances", "exhibitions", "major", "theatre", "festival", "poland", "combining", "theatre", "science", "criticism", "arts", "music", "film", "organized", "biannually", "since", "1993", "celebration", "city", "patron", "saint", "casimir", "jagiellon", "taking", "place", "march", "2011", "celebrated", "4th", "6th", "march", "religious", "celebrations", "sports", "cultural", "events", "well", "concerts", "annual", "festival", "early", "music", "takes", "place", "october", "biannual", "air", "show", "next", "festival", "scheduled", "august", "2015", "biggest", "event", "poland", "attracting", "tens", "thousands", "visitors", "poland", "abroad", "annual", "poland", "wide", "festival", "shanties", "technical", "university", "radom", "10", "000", "students", "enrolled", "radom", "largest", "institute", "higher", "education", "offers", "variety", "courses", "programs", "choose", "language", "school", "offering", "courses", "english", "german", "italian", "spanish", "russian", "french", "language", "school", "offering", "courses", "arabic", "english", "german", "italian", "spanish", "french", "buy", "local", "non", "pasteurized", "beer", "one", "radom", "first", "micro", "breweries", "said", "recipes", "date", "back", "hundred", "years", "ago", "locally", "made", "cocoa", "cake", "whipped", "cream", "ask", "restaurants", "confectioneries", "cafeteria", "style", "place", "serving", "polish", "european", "cuisine", "place", "go", "quick", "meal", "cake", "coffee", "nothing", "special", "though", "restaurant", "serving", "balkan", "cuisine", "located", "basement", "19th", "century", "bath", "house", "traditional", "polish", "restaurant", "stylized", "movie", "casablanca", "restaurant", "serves", "polish", "european", "cuisine", "also", "popular", "go", "couple", "beers", "nice", "music", "plays", "background", "city", "first", "vegetarian", "restaurant", "extravagant", "design", "friendly", "atmosphere", "japanese", "restaurant", "traditional", "restaurant", "decorated", "highland", "style", "newly", "opened", "family", "restaurant", "great", "place", "visit", "children", "engage", "number", "educational", "activities", "eat", "cosy", "restaurant", "serving", "italian", "cuisine", "piano", "bar", "every", "tuesday", "wielogora", "near", "radom", "ul", "warszawska", "98", "100", "located", "hotel", "u", "grubego", "traditional", "polish", "restaurant", "located", "europejski", "hotel", "restaurant", "offers", "variety", "polish", "international", "cuisine", "ladies", "club", "cafe", "apart", "numerous", "drinks", "cocktails", "food", "desserts", "available", "two", "storey", "cosy", "pub", "live", "music", "bar", "restaurant", "bowling", "pool", "karaoke", "every", "tuesday", "thursday", "21", "00", "small", "lively", "pub", "next", "train", "station", "popular", "watching", "football", "matches", "first", "restaurant", "radom", "house", "microbrewery", "go", "meal", "chase", "one", "4", "kinds", "beer", "brewed", "pivovaria", "brand", "new", "club", "restaurant", "serving", "variety", "beer", "whiskey", "liqueurs", "sailors", "tavern", "student", "club", "located", "basement", "faculty", "economics", "student", "club", "located", "19th", "century", "basement", "ex", "russian", "garrison", "building", "lounge", "club", "minimum", "age", "25", "largest", "venue", "radom", "1000", "people", "capacity", "concerts", "organized", "regular", "basis", "bowling", "pool", "available", "youth", "hostel", "oldest", "continuously", "operating", "hotel", "city"], "attractions": {"Academic Art Gallery \"Rogatka\"": {"type": "see", "description": ["corner", "malczewskiego", "kelles", "krauza", "streets", "polish", "gallery", "faculty", "arts", "technical", "university", "radom", "located", "19th", "century", "toll", "house", "building", "entry", "city", "used"], "coordinates": [NaN, NaN], "website": "http://www.wydzialsztuki.pr.radom.pl/rogatka/index.html", "place_id": null, "reviews": null}, "Jacek Malczewski Museum": {"type": "see", "description": ["polish"], "coordinates": [NaN, NaN], "website": "http://www.muzeum.edu.pl", "place_id": null, "reviews": null}, "Mazowieckie Centrum Sztuki Wsp\u00f3\u0142czesnej 'ELEKTROWNIA": {"type": "see", "description": ["polish", "centre", "contemporary", "art", "temporarily", "moved", "away", "location", "ul", "kopernika", "1", "time", "renovation"], "coordinates": [NaN, NaN], "website": "http://www.elektrownia.art.pl", "place_id": null, "reviews": null}, "Muzeum Sztuki Wsp\u00f3\u0142czesnej": {"type": "see", "description": ["rynek", "4", "5", "museum", "contemporary", "arts", "established", "1990", "first", "contemporary", "arts", "dedicated", "museum", "poland", "boasts", "collection", "3", "500", "exhibits"], "coordinates": [NaN, NaN], "website": "nan", "place_id": null, "reviews": null}, "Muzeum Wsi Radomskiej": {"type": "see", "description": ["polish", "open", "air", "museum", "radom", "region", "country", "side", "great", "place", "weekend", "visit", "try", "get", "one", "numerous", "events", "organize"], "coordinates": [NaN, NaN], "website": "http://www.muzeum-radom.pl", "place_id": null, "reviews": null}, "Bernardine Monastery": {"type": "see", "description": ["polish", "one", "unique", "sights", "radom", "founded", "1468", "one", "oldest", "bernardine", "monasteries", "world"], "coordinates": [NaN, NaN], "website": "http://www.radom.bernardyni.pl/", "place_id": null, "reviews": null}, "Holy Family Church": {"type": "see", "description": ["polish", "neo", "gothic", "church", "build", "1905"], "coordinates": [NaN, NaN], "website": "http://www.rodzina.radom.pl/", "place_id": "ChIJJ1_I_xAO04kRnmjfGWMB2FA", "reviews": null}, "Holy Virgin Mary Cathedral": {"type": "see", "description": ["polish", "radom", "cathedral", "build", "1898", "1918"], "coordinates": [NaN, NaN], "website": "http://katedra.radom.opoka.org.pl/", "place_id": null, "reviews": null}, "Lutheran Church": {"type": "see", "description": ["polish"], "coordinates": [NaN, NaN], "website": "http://www.radom.luteranie.pl/", "place_id": "not found", "reviews": null}, "St. John the Baptist Church": {"type": "see", "description": ["polish", "one", "oldest", "churches", "radom", "originally", "founded", "1360", "king", "casimir", "great", "sure", "see", "17th", "century", "chapel", "founded", "jan", "kochanowski"], "coordinates": [NaN, NaN], "website": "http://www.fara.radom.pl/", "place_id": "ChIJ79Vo8KM8bEcRDr5PY6-CmoQ", "reviews": null}, "St. Stanislaus Garrison Church": {"type": "see", "description": ["plac", "konstytucji", "3", "maja", "1", "originally", "built", "1902", "eastern", "orthodox", "church", "serves", "roman", "catholic", "military", "church"], "coordinates": [NaN, NaN], "website": "nan", "place_id": null, "reviews": null}, "St. Wenceslaus Church": {"type": "see", "description": ["polish", "oldest", "remaining", "building", "city", "likely", "build", "1216"], "coordinates": [NaN, NaN], "website": "http://waclaw.radom.pl/", "place_id": "ChIJYfr9QKLND4gRtdjKX5DRZtM", "reviews": {"html_attributions": [], "result": {"rating": 4.5, "reviews": [{"author_name": "Cynthia Torres", "author_url": "https://www.google.com/maps/contrib/115050273979104091501/reviews", "language": "en", "profile_photo_url": "https://lh3.googleusercontent.com/--4aESTkvL3s/AAAAAAAAAAI/AAAAAAAAAEE/pxXVmesnPrY/s128-c0x00000000-cc-rp-mo-ba3/photo.jpg", "rating": 4, "relative_time_description": "5 months ago", "text": "I have been going to this church for a while and it is very friendly.", "time": 1539892026}, {"author_name": "Luis R", "author_url": "https://www.google.com/maps/contrib/102087842629343707898/reviews", "language": "en", "profile_photo_url": "https://lh5.googleusercontent.com/-JojLlO7aD3A/AAAAAAAAAAI/AAAAAAAACfU/sSiae3WXp1U/s128-c0x00000000-cc-rp-mo-ba2/photo.jpg", "rating": 4, "relative_time_description": "4 weeks ago", "text": "Catholic church", "time": 1552629100}, {"author_name": "Linda Ford", "author_url": "https://www.google.com/maps/contrib/101750605680415394153/reviews", "language": "en", "profile_photo_url": "https://lh4.googleusercontent.com/-2A36tW7Z994/AAAAAAAAAAI/AAAAAAAAAAA/ACHi3rfADJpMmoFGIpfsQonqEvRc422jtg/s128-c0x00000000-cc-rp-mo-ba3/photo.jpg", "rating": 5, "relative_time_description": "4 years ago", "text": "Beautiful Church. Attended elementary school here in the 60's.", "time": 1414641802}, {"author_name": "Estefan\u00eda Chimborazo", "author_url": "https://www.google.com/maps/contrib/114942907429765714930/reviews", "language": "en", "profile_photo_url": "https://lh3.googleusercontent.com/-OeKwp2LDl6Q/AAAAAAAAAAI/AAAAAAAAAKk/UxU1A-EdWZI/s128-c0x00000000-cc-rp-mo/photo.jpg", "rating": 5, "relative_time_description": "3 years ago", "text": "I have went there a lot of times", "time": 1450937277}, {"author_name": "raul castaneda", "author_url": "https://www.google.com/maps/contrib/113706331303304607382/reviews", "language": "es", "profile_photo_url": "https://lh5.googleusercontent.com/-o5d0EbgJsf0/AAAAAAAAAAI/AAAAAAAACqY/UwKWUw6VyXU/s128-c0x00000000-cc-rp-mo/photo.jpg", "rating": 5, "relative_time_description": "4 months ago", "text": "He asistido  hace poco m\u00e1s de 4 meses ,las personas que ayudan son muy amigables pero lo que es el padre Benjam\u00edn Ar\u00e9valo es de lo mejor que yo aya visto ,es tan agradable asistir a las misas que el imparte que te hace sentir excelentemente bien ,y creo que las palabras son pocas con las que yo pueda expresarlo , tienen que vivirlo para saberlo.", "time": 1544755972}]}, "status": "OK"}}, "Radomska Orkiestra Kameralna": {"type": "do", "description": ["go", "performance", "city", "renowned", "chamber", "orchestra"], "coordinates": [NaN, NaN], "website": "http://www.rok.art.pl/", "place_id": null, "reviews": null}, "Teatr Powszechny im. Jana Kochanowskiego": {"type": "do", "description": ["see", "theatre", "play", "jan", "kochanowski", "popular", "theatre", "radom"], "coordinates": [NaN, NaN], "website": "http://www.teatr.radom.pl", "place_id": null, "reviews": null}, "Dni Radomia": {"type": "do", "description": ["city", "annual", "festivity", "taking", "place", "around", "middle", "june", "expect", "large", "number", "concerts", "performances", "exhibitions"], "coordinates": [NaN, NaN], "website": "http://www.radom.pl", "place_id": null, "reviews": null}, "International Gombrowicz Festival": {"type": "do", "description": ["major", "theatre", "festival", "poland", "combining", "theatre", "science", "criticism", "arts", "music", "film", "organized", "biannually", "since", "1993"], "coordinates": [NaN, NaN], "website": "http://www.teatr.radom.pl/mfg.html", "place_id": null, "reviews": null}, "Kaziki": {"type": "do", "description": ["celebration", "city", "patron", "saint", "casimir", "jagiellon", "taking", "place", "march", "2011", "celebrated", "4th", "6th", "march", "religious", "celebrations", "sports", "cultural", "events", "well", "concerts"], "coordinates": [NaN, NaN], "website": "http://www.radom.pl", "place_id": null, "reviews": null}, "Mi\u0119dzynarodowy Festiwal Muzyki Dawnej im. Miko\u0142aja z Radomia": {"type": "do", "description": ["annual", "festival", "early", "music", "takes", "place", "october"], "coordinates": [NaN, NaN], "website": "http://www.festiwal.radom.pl/english.html {{dead link|May 2016}}", "place_id": null, "reviews": null}, "Radom Air Show": {"type": "do", "description": ["biannual", "air", "show", "next", "festival", "scheduled", "august", "2015", "biggest", "event", "poland", "attracting", "tens", "thousands", "visitors", "poland", "abroad"], "coordinates": [NaN, NaN], "website": "http://www.airshow.sp.mil.pl/", "place_id": null, "reviews": null}, "Og\u00f3lnopolskie Spotkania z Piosenk\u0105 \u017beglarsk\u0105 RAFA": {"type": "do", "description": ["annual", "poland", "wide", "festival", "shanties"], "coordinates": [NaN, NaN], "website": "http://www.bradeli.pl/", "place_id": null, "reviews": null}, "Browar Zamkowy - Piwo \u017bywe": {"type": "buy", "description": ["buy", "local", "non", "pasteurized", "beer", "one", "radom", "first", "micro", "breweries", "said", "recipes", "date", "back", "hundred", "years", "ago"], "coordinates": [NaN, NaN], "website": "http://www.browar.radom.pl/", "place_id": null, "reviews": null}, "Radomianka": {"type": "buy", "description": ["locally", "made", "cocoa", "cake", "whipped", "cream", "ask", "restaurants", "confectioneries"], "coordinates": [NaN, NaN], "website": "nan", "place_id": null, "reviews": null}, "Galeria 'Echo'": {"type": "buy", "description": ["nan"], "coordinates": [NaN, NaN], "website": "nan", "place_id": null, "reviews": null}, "M1 Shopping Center": {"type": "buy", "description": ["nan"], "coordinates": [NaN, NaN], "website": "http://www.radom.m1-centrum.pl/", "place_id": null, "reviews": null}, "'Senior' Department Store": {"type": "buy", "description": ["nan"], "coordinates": [NaN, NaN], "website": "nan", "place_id": null, "reviews": null}, "Galeria S\u0142oneczna": {"type": "buy", "description": ["nan"], "coordinates": [NaN, NaN], "website": "nan", "place_id": null, "reviews": null}, "Pod Kasztanami": {"type": "eat", "description": ["nan"], "coordinates": [NaN, NaN], "website": "http://www.3xstudio.pl/pod_kasztanami/", "place_id": null, "reviews": null}, "S\u0142onecznik": {"type": "eat", "description": ["cafeteria", "style", "place", "serving", "polish", "european", "cuisine", "place", "go", "quick", "meal", "cake", "coffee", "nothing", "special", "though"], "coordinates": [NaN, NaN], "website": "nan", "place_id": null, "reviews": null}, "Banja Luka Restaurant & Bar": {"type": "eat", "description": ["restaurant", "serving", "balkan", "cuisine", "located", "basement", "19th", "century", "bath", "house"], "coordinates": [NaN, NaN], "website": "http://www.banja-luka.pl/", "place_id": null, "reviews": null}, "Bar u Grubego": {"type": "eat", "description": ["traditional", "polish", "restaurant"], "coordinates": [NaN, NaN], "website": "http://hotelwradomiu.pl/pl/restauracje,przeglad-artykulow,84,570", "place_id": null, "reviews": null}, "Casablanca Piano Cafe": {"type": "eat", "description": ["stylized", "movie", "casablanca", "restaurant", "serves", "polish", "european", "cuisine", "also", "popular", "go", "couple", "beers", "nice", "music", "plays", "background"], "coordinates": [NaN, NaN], "website": "nan", "place_id": null, "reviews": null}, "Green Zebra": {"type": "eat", "description": ["city", "first", "vegetarian", "restaurant", "extravagant", "design", "friendly", "atmosphere"], "coordinates": [NaN, NaN], "website": "http://www.greenzebra.pl {{dead link|May 2016}}", "place_id": null, "reviews": null}, "Higashi Sushi Bar": {"type": "eat", "description": ["japanese", "restaurant"], "coordinates": [NaN, NaN], "website": "http://www.higashi.pl {{dead link|May 2016}}", "place_id": null, "reviews": null}, "Karczma Bankrut": {"type": "eat", "description": ["traditional", "restaurant", "decorated", "highland", "style"], "coordinates": [NaN, NaN], "website": "http://www.karczmabankrut.pl", "place_id": null, "reviews": null}, "MammaLeo": {"type": "eat", "description": ["newly", "opened", "family", "restaurant", "great", "place", "visit", "children", "engage", "number", "educational", "activities", "eat"], "coordinates": [NaN, NaN], "website": "http://www.mammaleo.pl", "place_id": null, "reviews": null}, "Olivio": {"type": "eat", "description": ["nan"], "coordinates": [NaN, NaN], "website": "http://www.restauracjaolivio.pl/", "place_id": null, "reviews": null}, "Panie i Panowie": {"type": "eat", "description": ["nan"], "coordinates": [NaN, NaN], "website": "nan", "place_id": null, "reviews": null}, "Teatralna": {"type": "eat", "description": ["cosy", "restaurant", "serving", "italian", "cuisine", "piano", "bar", "every", "tuesday"], "coordinates": [NaN, NaN], "website": "http://www.teatralna.radom.pl/", "place_id": null, "reviews": null}, "Restauracja u Grubego": {"type": "eat", "description": ["wielogora", "near", "radom", "ul", "warszawska", "98", "100", "located", "hotel", "u", "grubego", "traditional", "polish", "restaurant"], "coordinates": [NaN, NaN], "website": "http://hotelwradomiu.pl/pl/restauracje,przeglad-artykulow,84,570", "place_id": null, "reviews": null}, "Europejska": {"type": "eat", "description": ["located", "europejski", "hotel", "restaurant", "offers", "variety", "polish", "international", "cuisine"], "coordinates": [NaN, NaN], "website": "http://www.europejska.radom.pl/index.php?lang=en {{dead link|May 2016}}", "place_id": null, "reviews": null}, "Babie Lato": {"type": "drink", "description": ["ladies", "club", "cafe", "apart", "numerous", "drinks", "cocktails", "food", "desserts", "available"], "coordinates": [NaN, NaN], "website": "http://www.babielato.radom.pl/ {{dead link|May 2016}}", "place_id": null, "reviews": null}, "Jack Rocks": {"type": "drink", "description": ["two", "storey", "cosy", "pub", "live", "music"], "coordinates": [NaN, NaN], "website": "nan", "place_id": null, "reviews": null}, "MK Bowling": {"type": "drink", "description": ["bar", "restaurant", "bowling", "pool", "karaoke", "every", "tuesday", "thursday", "21", "00"], "coordinates": [NaN, NaN], "website": "http://www.mkbowling.pl/start-radom", "place_id": null, "reviews": null}, "Nasza Szkapa": {"type": "drink", "description": ["small", "lively", "pub", "next", "train", "station", "popular", "watching", "football", "matches"], "coordinates": [NaN, NaN], "website": "nan", "place_id": null, "reviews": null}, "Pivovaria": {"type": "drink", "description": ["first", "restaurant", "radom", "house", "microbrewery", "go", "meal", "chase", "one", "4", "kinds", "beer", "brewed", "pivovaria"], "coordinates": [NaN, NaN], "website": "http://www.pivovaria.pl/", "place_id": null, "reviews": null}, "Retrospekcja": {"type": "drink", "description": ["brand", "new", "club", "restaurant", "serving", "variety", "beer", "whiskey", "liqueurs"], "coordinates": [NaN, NaN], "website": "http://www.retrospekcja.radom.pl/ {{dead link|May 2016}}", "place_id": null, "reviews": null}, "Tawerna MESSA": {"type": "drink", "description": ["sailors", "tavern"], "coordinates": [NaN, NaN], "website": "nan", "place_id": null, "reviews": null}, "Bufet artystyczny Czekolada": {"type": "drink", "description": ["nan"], "coordinates": [NaN, NaN], "website": "nan", "place_id": null, "reviews": null}, "Dekada": {"type": "drink", "description": ["nan"], "coordinates": [NaN, NaN], "website": "http://www.cafe-dekada.pl {{dead link|May 2016}}", "place_id": null, "reviews": null}, "Marcus": {"type": "drink", "description": ["nan"], "coordinates": [NaN, NaN], "website": "nan", "place_id": null, "reviews": null}, "Aula": {"type": "drink", "description": ["student", "club", "located", "basement", "faculty", "economics"], "coordinates": [NaN, NaN], "website": "http://www.aula.radom.pl/", "place_id": null, "reviews": null}, "Alibi": {"type": "drink", "description": ["student", "club", "located", "19th", "century", "basement", "ex", "russian", "garrison", "building"], "coordinates": [NaN, NaN], "website": "http://alibiklub.pl/", "place_id": "ChIJm7rkMcufpkARO8y3p7aCws4", "reviews": null}, "Archiwum": {"type": "drink", "description": ["lounge", "club"], "coordinates": [NaN, NaN], "website": "http://www.archiwumclub.pl/", "place_id": null, "reviews": null}, "Club Mojito": {"type": "drink", "description": ["minimum", "age", "25"], "coordinates": [NaN, NaN], "website": "http://www.clubmojito.pl/", "place_id": null, "reviews": null}, "Fanaberia": {"type": "drink", "description": ["nan"], "coordinates": [NaN, NaN], "website": "http://www.fanaberia.pl/", "place_id": null, "reviews": null}, "Katakumby": {"type": "drink", "description": ["nan"], "coordinates": [NaN, NaN], "website": "http://www.katakumby.radom.pl", "place_id": null, "reviews": null}, "Strefa G2": {"type": "drink", "description": ["largest", "venue", "radom", "1000", "people", "capacity", "concerts", "organized", "regular", "basis", "bowling", "pool", "available"], "coordinates": [NaN, NaN], "website": "http://www.g2.radom.pl", "place_id": null, "reviews": null}, "Szkolne Schronisko M\u0142odzie\u017cowe": {"type": "sleep", "description": ["youth", "hostel"], "coordinates": [NaN, NaN], "website": "http://www.ssmradom.pl/", "place_id": null, "reviews": null}, "Hotel Astor": {"type": "sleep", "description": ["nan"], "coordinates": [NaN, NaN], "website": "http://www.hotel-astor.pl/", "place_id": "ChIJRVD4n6lJ2YAR1YSVb3HIUuM", "reviews": null}, "Hotel \u201eCentralny O\u015brodek Szkolenia Maszynist\u00f3w\u201d": {"type": "sleep", "description": ["nan"], "coordinates": [NaN, NaN], "website": "nan", "place_id": null, "reviews": null}, "E7": {"type": "sleep", "description": ["nan"], "coordinates": [NaN, NaN], "website": "http://www.hotele7.radom.pl {{dead link|May 2016}}", "place_id": null, "reviews": null}, "Glass": {"type": "sleep", "description": ["nan"], "coordinates": [NaN, NaN], "website": "http://hotelglass.radom.pl/?ver=ang", "place_id": null, "reviews": null}, "Hotel Gromada - Centrum": {"type": "sleep", "description": [], "coordinates": [NaN, NaN], "website": "http://www.gromada.pl/en-hotel-show-77.html {{dead link|May 2016}}", "place_id": null, "reviews": null}, "Hotel Gromada - Borki": {"type": "sleep", "description": [], "coordinates": [NaN, NaN], "website": "http://www.gromada.pl/en-hotel-gromada-radom_borki_en.html {{dead link|May 2016}}", "place_id": null, "reviews": null}, "Hotel u Grubego Radom": {"type": "sleep", "description": [], "coordinates": [NaN, NaN], "website": "http://hotelwradomiu.pl", "place_id": null, "reviews": null}, "Gryf": {"type": "sleep", "description": ["nan"], "coordinates": [NaN, NaN], "website": "http://www.hotelgryf.radom.pl", "place_id": null, "reviews": null}, "Hotel Iskra": {"type": "sleep", "description": ["oldest", "continuously", "operating", "hotel", "city"], "coordinates": [NaN, NaN], "website": "http://www.hoteliskra.radom.pl", "place_id": null, "reviews": null}, "Hotel Poniatowski Radom": {"type": "sleep", "description": [], "coordinates": [NaN, NaN], "website": "http://www.hotelponiatowski.radom.pl", "place_id": null, "reviews": null}, "Hotel TM": {"type": "sleep", "description": ["nan"], "coordinates": [NaN, NaN], "website": "http://www.hoteltm.pl/index_en.html {{dead link|May 2016}}", "place_id": null, "reviews": null}, "Hotel Aviator": {"type": "sleep", "description": [], "coordinates": [NaN, NaN], "website": "http://www.aviatorhotel.com.pl", "place_id": null, "reviews": null}, "Hotel Europejski": {"type": "sleep", "description": [], "coordinates": [NaN, NaN], "website": "http://www.hoteleuropejski.radom.pl", "place_id": null, "reviews": null}}}}